{
    "name": "Orchestra Solution",
    "version": "0.1",
    "projects": [
        {
            "name": "php-orchestra/application",
            "path": "./application"
        },
        {
            "name": "php-orchestra/domain",
            "path": "./domain"
        },
        {
            "name": "php-orchestra/cli",
            "path": ".\\cli",
            "referencedProjects": [
                {
                    "name": "php-orchestra/application",
                    "path": ".\\application"
                }
            ]
        }
    ]
}